.mypy_cache/3.9/jupyter_server/__init__.data.json
.mypy_cache/3.9/jupyter_server/__init__.meta.json
.mypy_cache/3.9/jupyter_server/_version.data.json
.mypy_cache/3.9/jupyter_server/_version.meta.json
examples/authorization/jupyter_nbclassic_readonly_config.py
examples/authorization/jupyter_nbclassic_rw_config.py
examples/authorization/jupyter_temporary_config.py
examples/identity/system_password/jupyter_server_config.py
examples/simple/conftest.py
examples/simple/jupyter_server_config.py
examples/simple/jupyter_simple_ext11_config.py
examples/simple/jupyter_simple_ext1_config.py
examples/simple/jupyter_simple_ext2_config.py
examples/simple/setup.py
examples/simple/simple_ext1/__init__.py
examples/simple/simple_ext1/__main__.py
examples/simple/simple_ext1/application.py
examples/simple/simple_ext1/handlers.py
examples/simple/simple_ext11/__init__.py
examples/simple/simple_ext11/__main__.py
examples/simple/simple_ext11/application.py
examples/simple/simple_ext2/__init__.py
examples/simple/simple_ext2/__main__.py
examples/simple/simple_ext2/application.py
examples/simple/simple_ext2/handlers.py
jupyter_server/.jupyter_ystore.db
jupyter_server/__init__.py
jupyter_server/__main__.py
jupyter_server/_sysinfo.py
jupyter_server/_tz.py
jupyter_server/_version.py
jupyter_server/config_manager.py
jupyter_server/log.py
jupyter_server/py.typed
jupyter_server/pytest_plugin.py
jupyter_server/serverapp.py
jupyter_server/traittypes.py
jupyter_server/transutils.py
jupyter_server/utils.py
jupyter_server/auth/__init__.py
jupyter_server/auth/__main__.py
jupyter_server/auth/authorizer.py
jupyter_server/auth/decorator.py
jupyter_server/auth/identity.py
jupyter_server/auth/login.py
jupyter_server/auth/logout.py
jupyter_server/auth/security.py
jupyter_server/auth/utils.py
jupyter_server/base/__init__.py
jupyter_server/base/handlers.py
jupyter_server/base/zmqhandlers.py
jupyter_server/event_schemas/contents_service/v1.yaml
jupyter_server/extension/__init__.py
elixir_server-2.1.0.dev205.dist-info/METADATA
elixir_server-2.1.0.dev205.dist-info/WHEEL
elixir_server-2.1.0.dev205.dist-info/entry_points.txt
elixir_server-2.1.0.dev205.dist-info/licenses/COPYING.md
elixir_server-2.1.0.dev205.dist-info/RECORD
