Metadata-Version: 2.1
Name: elixir_server
Version: 2.1.0.dev205
Summary: The backend—i.e. core services, APIs, and REST endpoints—to Elixir web applications.
Project-URL: Homepage, https://ciusji.gitbook.io/elixirnote/guides/elixirnote-server
Project-URL: Documentation, https://ciusji.gitbook.io/elixirnote/guides/elixirnote-server
Project-URL: Funding, https://numfocus.org/donate
Project-URL: Source, https://github.com/ElixirNote/elixirserver
Project-URL: Tracker, https://github.com/ElixirNote/elixirserver/issues
Author-email: ciusji <bqjimaster@gmail.com>
License: # Licensing terms
License-File: COPYING.md
Keywords: ipython,jupyter
Classifier: Development Status :: 5 - Production/Stable
Classifier: Framework :: Jupyter
Classifier: Intended Audience :: Developers
Classifier: Intended Audience :: Science/Research
Classifier: Intended Audience :: System Administrators
Classifier: License :: OSI Approved :: BSD License
Classifier: Programming Language :: Python
Classifier: Programming Language :: Python :: 3
Classifier: Programming Language :: Python :: 3 :: Only
Classifier: Programming Language :: Python :: 3.7
Classifier: Programming Language :: Python :: 3.8
Classifier: Programming Language :: Python :: 3.9
Classifier: Programming Language :: Python :: 3.10
Requires-Python: >=3.7
Requires-Dist: anyio<4,>=3.1.0
Requires-Dist: argon2-cffi
Requires-Dist: jinja2
Requires-Dist: jupyter-client>=6.1.12
Requires-Dist: jupyter-core>=4.7.0
Requires-Dist: jupyter-events>=0.4.0
Requires-Dist: jupyter-server-terminals
Requires-Dist: nbconvert>=6.4.4
Requires-Dist: nbformat>=5.2.0
Requires-Dist: packaging
Requires-Dist: prometheus-client
Requires-Dist: pywinpty; os_name == 'nt'
Requires-Dist: pyzmq>=17
Requires-Dist: send2trash
Requires-Dist: terminado>=0.8.3
Requires-Dist: tornado>=6.1.0
Requires-Dist: traitlets>=5.1
Requires-Dist: websocket-client
Provides-Extra: dev
Requires-Dist: coverage; extra == 'dev'
Requires-Dist: pre-commit; extra == 'dev'
Requires-Dist: pytest-cov; extra == 'dev'
Provides-Extra: test
Requires-Dist: ipykernel; extra == 'test'
Requires-Dist: pytest-console-scripts; extra == 'test'
Requires-Dist: pytest-timeout; extra == 'test'
Requires-Dist: pytest-tornasync; extra == 'test'
Requires-Dist: pytest>=6.0; extra == 'test'
Requires-Dist: requests; extra == 'test'
